cleanfusion/__init__.py
cleanfusion/cli.py
cleanfusion/core/__init__.py
cleanfusion/core/data_assessment.py
cleanfusion/core/data_preprocessor.py
cleanfusion/core/decision_engine.py
cleanfusion/core/missing_value_handler.py
cleanfusion/core/outlier_handler.py
cleanfusion/file_handlers/__init__.py
cleanfusion/file_handlers/csv_handler.py
cleanfusion/file_handlers/docx_handler.py
cleanfusion/file_handlers/pdf_handler.py
cleanfusion/file_handlers/txt_handler.py
cleanfusion/text/__init__.py
cleanfusion/text/categorical_encoder.py
cleanfusion/text/text_cleaner.py
cleanfusion/text/text_vectorizer.py
cleanfusion/utils/__init__.py
cleanfusion/utils/logger.py
cleanfusion-0.1.9.dist-info/licenses/LICENSE
cleanfusion-0.1.9.dist-info/METADATA
cleanfusion-0.1.9.dist-info/WHEEL
cleanfusion-0.1.9.dist-info/entry_points.txt
cleanfusion-0.1.9.dist-info/top_level.txt
cleanfusion-0.1.9.dist-info/RECORD
