Metadata-Version: 2.4
Name: cleanfusion
Version: 0.1.9
Summary: A comprehensive data cleaning library
Home-page: https://github.com/himanshuchopade97/CleanFusion
Author: Hriday Thaker,Himanshu Chopade,Gautam Rajhans,Aryan Bachute
Author-email: Himanshu Chopade <himanshuchopade97@gmail.com>, Hriday Thaker <hriday.thaker2604@gmail.com>, Aryan Bachute <bachutearyan@gmail.com>, Gautam Rajhans <gprajhans@gmail.com>
License: MIT
Project-URL: Homepage, https://github.com/himanshuchopade97/CleanFusion
Project-URL: Bug Tracker, https://github.com/himanshuchopade97/CleanFusion/issues
Classifier: Programming Language :: Python :: 3
Classifier: Programming Language :: Python :: 3.7
Classifier: Programming Language :: Python :: 3.8
Classifier: Programming Language :: Python :: 3.9
Classifier: Programming Language :: Python :: 3.10
Classifier: License :: OSI Approved :: MIT License
Classifier: Operating System :: OS Independent
Classifier: Development Status :: 3 - Alpha
Classifier: Intended Audience :: Developers
Classifier: Intended Audience :: Science/Research
Classifier: Topic :: Scientific/Engineering :: Information Analysis
Classifier: Topic :: Scientific/Engineering :: Artificial Intelligence
Requires-Python: >=3.7
License-File: LICENSE
Requires-Dist: pandas>=1.3.0
Requires-Dist: numpy>=1.20.0
Requires-Dist: scikit-learn>=1.0.0
Requires-Dist: matplotlib>=3.4.0
Requires-Dist: nltk>=3.6.0
Requires-Dist: PyPDF2>=2.0.0
Requires-Dist: pdfplumber>=0.7.0
Requires-Dist: scipy>=1.7.0
Requires-Dist: python-docx>=0.8.11
Provides-Extra: bert
Requires-Dist: sentence-transformers>=2.2.0; extra == "bert"
Provides-Extra: pdf
Requires-Dist: pdfplumber>=0.7.0; extra == "pdf"
Provides-Extra: docx
Requires-Dist: python-docx>=0.8.11; extra == "docx"
Provides-Extra: dev
Requires-Dist: pytest>=7.0.0; extra == "dev"
Requires-Dist: black; extra == "dev"
Requires-Dist: isort; extra == "dev"
Provides-Extra: all
Requires-Dist: cleanfusion[bert,docx,pdf]; extra == "all"
Dynamic: author
Dynamic: home-page
Dynamic: license-file
Dynamic: requires-python
